2012-2/TPs/ED_06/462020-06/clock.v
// -------------------------
// clock.v – Gerador de clock
// Nome: Willian Antonio dos Santos
// Matricula: 462020
// -------------------------
// ---------------------------
// -- clock generator (1)
// ---------------------------
module clock ( clk );
       output clk;
       reg clk;
       initial begin
               clk = 1'b0;
       end
       always begin
           #12 clk = ~clk;
       end
endmodule // clock ( )

2012-2/TPs/ED_06/462020-06/Exemplo0045.v
// ---------------------------
// Exemplo0045 – Gerador de pulsos 1/2 freq CLK
// Nome: Willian Antonio dos Santos
// Matricula: 462020
// ---------------------------
`include "clock.v"
// ---------------------------
// -- pulso metade da frequencia do clock de Exemplo0041
// ---------------------------
module pulseMfk ( signal, clock );
       input clock;
       output signal;
       reg signal;
       initial begin
              signal = 1'b0;
       end
       always @ ( posedge clock ) begin
              signal = 1'b1;
           #24 signal = 1'b0;
           #24 signal = 1'b0;
       end
endmodule
// ---------------------------
// -- test pulseMfk
// ---------------------------
module Exemplo0045;
       wire clock;
       clock clk ( clock );
       wire p;
       pulseMfk pMfk ( p, clock );
       initial begin
               $dumpfile ( "Exemplo0045.vcd" );
               $dumpvars ( 1, clock, p );
          #480 $finish;
       end
endmodule

2012-2/TPs/ED_06/462020-06/Exemplo0045.vcd
$date
	Thu Oct 11 03:26:10 2012
$end
$version
	Icarus Verilog
$end
$timescale
	1s
$end
$scope module Exemplo0045 $end
$var wire 1 ! clock $end
$upscope $end
$scope module Exemplo0045 $end
$var wire 1 " p $end
$upscope $end
$enddefinitions $end
#0
$dumpvars
0"
0!
$end
#12
1"
1!
#24
0!
#36
1!
0"
#48
0!
#60
1"
1!
#72
0!
#84
1!
0"
#96
0!
#108
1"
1!
#120
0!
#132
1!
0"
#144
0!
#156
1"
1!
#168
0!
#180
1!
0"
#192
0!
#204
1"
1!
#216
0!
#228
1!
0"
#240
0!
#252
1"
1!
#264
0!
#276
1!
0"
#288
0!
#300
1"
1!
#312
0!
#324
1!
0"
#336
0!
#348
1"
1!
#360
0!
#372
1!
0"
#384
0!
#396
1"
1!
#408
0!
#420
1!
0"
#432
0!
#444
1"
1!
#456
0!
#468
1!
0"
