2012-1/TPs/Guia_06/03-23/396690/clock.v
// --------------------------- 
// -- test clock generator (1) 
// --------------------------- 
// Nome: Gabriel Benjamim de Carvalho
// Matricula: 396690

module clock ( clk ); 
output clk; 
reg clk; 
initial 
begin 
clk = 1'b0; 
end 
always 
begin 
#12 clk = ~clk; 
end 
endmodule 
module Exemplo0041; 
wire clk; 
clock CLK1 ( clk ); 
initial begin 
#120 $finish; 
end 
endmodule

2012-1/TPs/Guia_06/03-23/396690/Exemplo0044.v
// --------------------------- 
// -- test clock generator (4) 
// --------------------------- 
// Nome: Gabriel Benjamim de Carvalho
// Matricula: 396690

`include "clock.v" 
module pulse1 ( signal, clock ); 
input clock; 
output signal; 
reg signal; 
always @ ( posedge clock ) 
begin 
signal = 1'b1; 
#40 signal = 1'b0; 
#40 signal = 1'b1; 
#40 signal = 1'b0; 
#40 signal = 1'b1; 
#40 signal = 1'b0; 
end 
endmodule 
module pulse2 ( signal, clock ); 
input clock; 
output signal; 
reg signal; 
always @ ( posedge clock ) 
begin 
signal = 1'b1; 
#40 signal = 1'b0; 
end 
endmodule 
module pulse3 ( signal, clock ); 
input clock; 
output signal; 
reg signal; 
always @ ( negedge clock ) 
begin 
signal = 1'b1; 
#40 signal = 1'b0; 
#40 signal = 1'b1; 
end 
endmodule 
module pulse4 ( signal, clock ); 
input clock; 
output signal; 
reg signal; 
always @ ( negedge clock ) 
begin 
signal = 1'b1; 
#40 signal = 1'b0; 
#40 signal = 1'b1; 
#40 signal = 1'b0; 
end 
endmodule 
module Exemplo0044; 
wire clock; 
clock clk ( clock ); 
wire p1,p2,p3,p4; 
pulse1 pls1 ( p1, clock ); 
pulse2 pls2 ( p2, clock ); 
pulse3 pls3 ( p3, clock ); 
pulse4 pls4 ( p4, clock ); 
initial begin 
$dumpfile ( "Exemplo0044.vcd" ); 
$dumpvars ( 1, clock, p1, p2, p3, p4 ); 
#480 $finish; 
end 
endmodule

2012-1/TPs/Guia_06/03-23/396690/Exemplo0044.vcd
$date
	Thu Mar 22 14:11:56 2012
$end
$version
	Icarus Verilog
$end
$timescale
	1s
$end
$scope module Exemplo0044 $end
$var wire 1 ! clock $end
$upscope $end
$scope module Exemplo0044 $end
$var wire 1 " p1 $end
$upscope $end
$scope module Exemplo0044 $end
$var wire 1 # p2 $end
$upscope $end
$scope module Exemplo0044 $end
$var wire 1 $ p3 $end
$upscope $end
$scope module Exemplo0044 $end
$var wire 1 % p4 $end
$upscope $end
$enddefinitions $end
#0
$dumpvars
x%
x$
x#
x"
0!
$end
#12
1"
1#
1!
#24
1$
1%
0!
#36
1!
#48
0!
#52
0"
0#
#60
1#
1!
#64
0$
0%
#72
0!
#84
1!
#92
1"
#96
0!
#100
0#
#104
1$
1%
#108
1#
1!
